VERILOG/modules.v


// module for 1-bit Manchester Carry Circuit (MCC)
module mcc_1bit(
    input wire clk,
    input wire A,
    input wire B,
    input wire Cin,
    output reg Cout,
    output reg Sum
);

    wire P = A ^ B;
    wire G = A & B;

    always @(*) begin
        if (clk) begin
            // clk == 1 → do actual addition
            Cout = G | (P & Cin);
        end
        else begin
            // clk == 0 → define what you want here
            Cout = 1'b1;   // your original idea
        end
        Sum = P ^ Cin;
    end
endmodule


// Module for flip flop
module dff(
    input wire D,
    input wire clk,
    output reg Q
);
    always @(posedge clk) begin
        Q <= D;
    end
endmodule

VERILOG/dff_tb.v
// testbench for d flip flop

`include "modules.v"
module dff_tb;

    reg d;
    reg clk;
    wire y;
    
    // instantiate the dff module
    dff mod( d , clk, y);
    
    initial begin
        clk = 0;
        forever #5 clk = ~clk; // toggle clock every 5 time units
    end
    
    initial begin

        $dumpfile("dff_tb.vcd");
        $dumpvars(0, dff_tb);
        // monitor changes
    
        // apply test vectors
        d = 0; #10;
        d = 1; #10;
        d = 0; #10;
        d = 1; #10;
        d = 1; #10;
        d = 0; #10;
    
        // finish simulation
        $finish;
    end
endmodule

VERILOG/dff_tb.vcd
$date
	Tue Dec  2 16:43:38 2025
$end
$version
	Icarus Verilog
$end
$timescale
	1s
$end
$scope module dff_tb $end
$var wire 1 ! y $end
$var reg 1 " clk $end
$var reg 1 # d $end
$scope module mod $end
$var wire 1 # D $end
$var wire 1 " clk $end
$var reg 1 ! Q $end
$upscope $end
$upscope $end
$enddefinitions $end
$comment Show the parameter values. $end
$dumpall
$end
#0
$dumpvars
0#
0"
x!
$end
#5
0!
1"
#10
0"
1#
#15
1!
1"
#20
0"
0#
#25
0!
1"
#30
0"
1#
#35
1!
1"
#40
0"
#45
1"
#50
0"
0#
#55
0!
1"
