VERILOG/modules.v


// module for 1-bit Manchester Carry Circuit (MCC)
module mcc_1bit(
    input wire clk,
    input wire A,
    input wire B,
    input wire Cin,
    output reg Cout,
    output reg Sum
);

    wire P = A ^ B;
    wire G = A & B;

    always @(*) begin
        if (clk) begin
            // clk == 1 → do actual addition
            Cout = G | (P & Cin);
        end
        else begin
            // clk == 0 → define what you want here
            Cout = 1'b1;   // your original idea
        end
        Sum = P ^ Cin;
    end
endmodule


// Module for flip flop
module dff(
    input wire D,
    input wire clk,
    output reg Q
);
    always @(posedge clk) begin
        Q <= D;
    end
endmodule

VERILOG/mcl_5bit_with_ff_tb.v

// testbench for 5-bit MCC with input and output flip-flops

`include "modules.v"

module mcl_5bit_with_ff_tb;

    reg clk;
    reg [4:0] A, B;
    reg Cin;

    wire [4:0] A_in, B_in;
    wire Cin_in;

    wire [4:0] SUMin;
    wire Cout_in;

    wire [4:0] SUM;
    wire Cout;

    // input flipflops
    dff dffA0 (.D(A[0]), .clk(clk), .Q(A_in[0]));
    dff dffA1 (.D(A[1]), .clk(clk), .Q(A_in[1]));
    dff dffA2 (.D(A[2]), .clk(clk), .Q(A_in[2]));
    dff dffA3 (.D(A[3]), .clk(clk), .Q(A_in[3]));
    dff dffA4 (.D(A[4]), .clk(clk), .Q(A_in[4]));

    dff dffB0 (.D(B[0]), .clk(clk), .Q(B_in[0]));
    dff dffB1 (.D(B[1]), .clk(clk), .Q(B_in[1]));
    dff dffB2 (.D(B[2]), .clk(clk), .Q(B_in[2]));
    dff dffB3 (.D(B[3]), .clk(clk), .Q(B_in[3]));
    dff dffB4 (.D(B[4]), .clk(clk), .Q(B_in[4]));

    dff dffCin (.D(Cin), .clk(clk), .Q(Cin_in));

    // MCC chain
    wire C1, C2, C3, C4 , C5;

    mcc_1bit m0 (.A(A_in[0]), .B(B_in[0]), .Cin(Cin_in), .clk(~clk), .Sum(SUMin[0]), .Cout(C1));
    mcc_1bit m1 (.A(A_in[1]), .B(B_in[1]), .Cin(C1),     .clk(~clk), .Sum(SUMin[1]), .Cout(C2));
    mcc_1bit m2 (.A(A_in[2]), .B(B_in[2]), .Cin(C2),     .clk(~clk), .Sum(SUMin[2]), .Cout(C3));
    mcc_1bit m3 (.A(A_in[3]), .B(B_in[3]), .Cin(C3),     .clk(~clk), .Sum(SUMin[3]), .Cout(C4));
    mcc_1bit m4 (.A(A_in[4]), .B(B_in[4]), .Cin(C4),     .clk(~clk), .Sum(SUMin[4]), .Cout(C5));

    // output flipflops
    dff dffS0 (.D(SUMin[0]), .clk(clk), .Q(SUM[0]));
    dff dffS1 (.D(SUMin[1]), .clk(clk), .Q(SUM[1]));
    dff dffS2 (.D(SUMin[2]), .clk(clk), .Q(SUM[2]));
    dff dffS3 (.D(SUMin[3]), .clk(clk), .Q(SUM[3]));
    dff dffS4 (.D(SUMin[4]), .clk(clk), .Q(SUM[4]));
    dff dffCout (.D(C5), .clk(clk), .Q(Cout));

    // clock
    initial clk = 0;
    always #5 clk = ~clk; // time period of clock = 10

    // stimulus
    initial begin
        $dumpfile("mcl_5bit_with_ff_tb.vcd");
        $dumpvars(0, mcl_5bit_with_ff_tb);

        A = 0; B = 0; Cin = 0;
        #1;
        A = 5'd1; B = 5'd2; Cin = 0;
        #20;

        A = 5'd0; B = 5'd4; Cin = 1;
        #20;

        A = 5'd15; B = 5'd15; Cin = 0;
        #20;

        A = 5'd0; B = 5'd0; Cin = 0;
        #20;

        $finish;
    end

endmodule

VERILOG/mcl_5bit_with_ff_tb.vcd
$date
	Tue Dec  2 16:40:32 2025
$end
$version
	Icarus Verilog
$end
$timescale
	1s
$end
$scope module mcl_5bit_with_ff_tb $end
$var wire 5 ! SUMin [4:0] $end
$var wire 5 " SUM [4:0] $end
$var wire 1 # Cout $end
$var wire 1 $ Cin_in $end
$var wire 1 % C5 $end
$var wire 1 & C4 $end
$var wire 1 ' C3 $end
$var wire 1 ( C2 $end
$var wire 1 ) C1 $end
$var wire 5 * B_in [4:0] $end
$var wire 5 + A_in [4:0] $end
$var reg 5 , A [4:0] $end
$var reg 5 - B [4:0] $end
$var reg 1 . Cin $end
$var reg 1 / clk $end
$scope module dffA0 $end
$var wire 1 0 D $end
$var wire 1 / clk $end
$var reg 1 1 Q $end
$upscope $end
$scope module dffA1 $end
$var wire 1 2 D $end
$var wire 1 / clk $end
$var reg 1 3 Q $end
$upscope $end
$scope module dffA2 $end
$var wire 1 4 D $end
$var wire 1 / clk $end
$var reg 1 5 Q $end
$upscope $end
$scope module dffA3 $end
$var wire 1 6 D $end
$var wire 1 / clk $end
$var reg 1 7 Q $end
$upscope $end
$scope module dffA4 $end
$var wire 1 8 D $end
$var wire 1 / clk $end
$var reg 1 9 Q $end
$upscope $end
$scope module dffB0 $end
$var wire 1 : D $end
$var wire 1 / clk $end
$var reg 1 ; Q $end
$upscope $end
$scope module dffB1 $end
$var wire 1 < D $end
$var wire 1 / clk $end
$var reg 1 = Q $end
$upscope $end
$scope module dffB2 $end
$var wire 1 > D $end
$var wire 1 / clk $end
$var reg 1 ? Q $end
$upscope $end
$scope module dffB3 $end
$var wire 1 @ D $end
$var wire 1 / clk $end
$var reg 1 A Q $end
$upscope $end
$scope module dffB4 $end
$var wire 1 B D $end
$var wire 1 / clk $end
$var reg 1 C Q $end
$upscope $end
$scope module dffCin $end
$var wire 1 . D $end
$var wire 1 / clk $end
$var reg 1 $ Q $end
$upscope $end
$scope module dffCout $end
$var wire 1 / clk $end
$var wire 1 % D $end
$var reg 1 # Q $end
$upscope $end
$scope module dffS0 $end
$var wire 1 D D $end
$var wire 1 / clk $end
$var reg 1 E Q $end
$upscope $end
$scope module dffS1 $end
$var wire 1 F D $end
$var wire 1 / clk $end
$var reg 1 G Q $end
$upscope $end
$scope module dffS2 $end
$var wire 1 H D $end
$var wire 1 / clk $end
$var reg 1 I Q $end
$upscope $end
$scope module dffS3 $end
$var wire 1 J D $end
$var wire 1 / clk $end
$var reg 1 K Q $end
$upscope $end
$scope module dffS4 $end
$var wire 1 L D $end
$var wire 1 / clk $end
$var reg 1 M Q $end
$upscope $end
$scope module m0 $end
$var wire 1 N A $end
$var wire 1 O B $end
$var wire 1 $ Cin $end
$var wire 1 P G $end
$var wire 1 Q P $end
$var wire 1 R clk $end
$var reg 1 ) Cout $end
$var reg 1 S Sum $end
$upscope $end
$scope module m1 $end
$var wire 1 T A $end
$var wire 1 U B $end
$var wire 1 ) Cin $end
$var wire 1 V G $end
$var wire 1 W P $end
$var wire 1 X clk $end
$var reg 1 ( Cout $end
$var reg 1 Y Sum $end
$upscope $end
$scope module m2 $end
$var wire 1 Z A $end
$var wire 1 [ B $end
$var wire 1 ( Cin $end
$var wire 1 \ G $end
$var wire 1 ] P $end
$var wire 1 ^ clk $end
$var reg 1 ' Cout $end
$var reg 1 _ Sum $end
$upscope $end
$scope module m3 $end
$var wire 1 ` A $end
$var wire 1 a B $end
$var wire 1 ' Cin $end
$var wire 1 b G $end
$var wire 1 c P $end
$var wire 1 d clk $end
$var reg 1 & Cout $end
$var reg 1 e Sum $end
$upscope $end
$scope module m4 $end
$var wire 1 f A $end
$var wire 1 g B $end
$var wire 1 & Cin $end
$var wire 1 h G $end
$var wire 1 i P $end
$var wire 1 j clk $end
$var reg 1 % Cout $end
$var reg 1 k Sum $end
$upscope $end
$upscope $end
$enddefinitions $end
$comment Show the parameter values. $end
$dumpall
$end
#0
$dumpvars
xk
1j
xi
xh
xg
xf
xe
1d
xc
xb
xa
x`
x_
1^
x]
x\
x[
xZ
xY
1X
xW
xV
xU
xT
xS
1R
xQ
xP
xO
xN
xM
xL
xK
xJ
xI
xH
xG
xF
xE
xD
xC
0B
xA
0@
x?
0>
x=
0<
x;
0:
x9
08
x7
06
x5
04
x3
02
x1
00
0/
0.
b0 -
b0 ,
bx +
bx *
x)
x(
x'
x&
x%
x$
x#
bx "
bx !
$end
#1
1<
10
b10 -
b1 ,
#5
1D
0F
1H
1J
1L
1S
0Y
1_
1e
b11101 !
1k
1Q
0P
1W
0V
0]
0\
0c
0b
0i
0h
1N
0T
0Z
0`
0f
0O
1U
0[
0a
0g
11
03
05
07
b1 +
09
0;
1=
0?
0A
b10 *
0C
0$
1%
1&
1'
1(
1)
0j
0d
0^
0X
0R
1/
#10
0L
0J
0H
1F
0k
0%
0e
0&
0_
0'
b11 !
1Y
0(
0)
1j
1d
1^
1X
1R
0/
#15
0#
0M
0K
0I
1G
b11 "
1E
1L
1J
1H
0F
1k
1%
1e
1&
1_
1'
b11101 !
0Y
1(
1)
0j
0d
0^
0X
0R
1/
#20
0L
0J
0H
1F
0k
0%
0e
0&
0_
0'
b11 !
1Y
0(
0)
1j
1d
1^
1X
1R
0/
#21
0<
1>
00
1.
b100 -
b0 ,
#25
0Q
0W
1]
1D
0N
0U
1[
1S
b0 +
01
0=
b100 *
1?
1$
1L
1J
0H
1F
1k
1%
1e
1&
0_
1'
b11011 !
1Y
1(
1)
0j
0d
0^
0X
0R
1/
#30
0L
0J
1H
0F
0k
0%
0e
0&
1_
0'
b101 !
0Y
0(
0)
1j
1d
1^
1X
1R
0/
#35
1I
b101 "
0G
1L
1J
0H
1F
1k
1%
1e
1&
0_
1'
b11011 !
1Y
1(
1)
0j
0d
0^
0X
0R
1/
#40
0L
0J
1H
0F
0k
0%
0e
0&
1_
0'
b101 !
0Y
0(
0)
1j
1d
1^
1X
1R
0/
#41
1:
1<
1@
10
12
14
16
0.
b1111 -
b1111 ,
#45
0]
1\
1P
1V
1b
0D
1N
1T
1Z
1`
1O
1U
1a
0S
11
13
15
b1111 +
17
1;
1=
b1111 *
1A
0$
1L
1J
1H
1F
1k
1%
1e
1&
1_
1'
b11110 !
1Y
1(
1)
0j
0d
0^
0X
0R
1/
#50
0%
1j
1d
1^
1X
1R
0/
#55
1M
1K
1G
b11110 "
0E
1%
0j
0d
0^
0X
0R
1/
#60
0%
1j
1d
1^
1X
1R
0/
#61
0:
0<
0>
0@
00
02
04
06
b0 -
b0 ,
#65
0P
0V
0\
0b
0N
0T
0Z
0`
0O
0U
0[
0a
01
03
05
b0 +
07
0;
0=
0?
b0 *
0A
1%
0j
0d
0^
0X
0R
1/
#70
0L
0J
0H
0F
0k
0%
0e
0&
0_
0'
b0 !
0Y
0(
0)
1j
1d
1^
1X
1R
0/
#75
0M
0K
0I
b0 "
0G
1L
1J
1H
1F
1k
1%
1e
1&
1_
1'
b11110 !
1Y
1(
1)
0j
0d
0^
0X
0R
1/
#80
0L
0J
0H
0F
0k
0%
0e
0&
0_
0'
b0 !
0Y
0(
0)
1j
1d
1^
1X
1R
0/
