VERILOG/modules.v


// module for 1-bit Manchester Carry Circuit (MCC)
module mcc_1bit(
    input wire clk,
    input wire A,
    input wire B,
    input wire Cin,
    output reg Cout,
    output reg Sum
);

    wire P = A ^ B;
    wire G = A & B;

    always @(*) begin
        if (clk) begin
            // clk == 1 → do actual addition
            Cout = G | (P & Cin);
        end
        else begin
            // clk == 0 → define what you want here
            Cout = 1'b1;   // your original idea
        end
        Sum = P ^ Cin;
    end
endmodule


// Module for flip flop
module dff(
    input wire D,
    input wire clk,
    output reg Q
);
    always @(posedge clk) begin
        Q <= D;
    end
endmodule

VERILOG/mcl_1bit_tb.v

`include "modules.v"


module mcl_1bit_tb;

    reg clk;
    reg A;
    reg B;
    reg Cin;
    wire Sum;
    wire Cout;

    // instantiate the mcc_1bit module
    mcc_1bit mod( clk ,A , B , Cin , Cout , Sum );

    initial clk = 0;
    always #5 clk = ~clk; // time period of clock = 10
    
    initial begin
        $dumpfile("mcl_1bit_tb.vcd");
        $dumpvars(0, mcl_1bit_tb);

        A = 0; B = 0; Cin = 0;
        #10;

        A = 0; B = 1; Cin = 0;
        #10;

        A = 1; B = 0; Cin = 0;
        #10;

        A = 1; B = 1; Cin = 0;
        #10;

        A = 1; B = 1; Cin = 1;
        #10;

        A = 0; B = 1; Cin = 1;
        #10;

        A = 1; B = 0; Cin = 1;
        #10;

        A = 0; B = 0; Cin = 1;
        #10;

        $finish;
    end
endmodule

VERILOG/mcl_1bit_tb.vcd
$date
	Tue Dec  2 16:53:32 2025
$end
$version
	Icarus Verilog
$end
$timescale
	1s
$end
$scope module mcl_1bit_tb $end
$var wire 1 ! Sum $end
$var wire 1 " Cout $end
$var reg 1 # A $end
$var reg 1 $ B $end
$var reg 1 % Cin $end
$var reg 1 & clk $end
$scope module mod $end
$var wire 1 # A $end
$var wire 1 $ B $end
$var wire 1 % Cin $end
$var wire 1 ' G $end
$var wire 1 ( P $end
$var wire 1 & clk $end
$var reg 1 " Cout $end
$var reg 1 ! Sum $end
$upscope $end
$upscope $end
$enddefinitions $end
$comment Show the parameter values. $end
$dumpall
$end
#0
$dumpvars
0(
0'
0&
0%
0$
0#
1"
0!
$end
#5
0"
1&
#10
1!
1"
1(
0&
1$
#15
0"
1&
#20
1"
0&
0$
1#
#25
0"
1&
#30
0!
1"
0(
1'
0&
1$
#35
1&
#40
1!
0&
1%
#45
1&
#50
0!
1(
0'
0&
0#
#55
1&
#60
0&
0$
1#
#65
1&
#70
1!
0(
0&
0#
#75
0"
1&
#80
1"
0&
